quranallsbuforuni/__init__.py
quranallsbuforuni/quran1.py
Quransurehfateheh-1.dist-info/METADATA
Quransurehfateheh-1.dist-info/WHEEL
Quransurehfateheh-1.dist-info/top_level.txt
Quransurehfateheh-1.dist-info/RECORD
