Metadata-Version: 2.1
Name: Quransurehfateheh
Version: 1
Summary: Quransurehfateheh
Author: Masoud Shafiei
Author-email: masoudshafiei89@yahoo.com
Keywords: quran,sureh,fateheh
Classifier: Programming Language :: Python :: 3
